json_partial_python-0.1.3.dist-info/METADATA
json_partial_python-0.1.3.dist-info/WHEEL
json_partial_py/__init__.py
json_partial_py/json_partial_py.cpython-313-x86_64-linux-gnu.so
json_partial_python-0.1.3.dist-info/RECORD
