Metadata-Version: 2.4
Name: json_partial_python
Version: 0.1.3
Classifier: Intended Audience :: Developers
Classifier: Programming Language :: Python :: 3.8
Classifier: Programming Language :: Python :: 3.9
Classifier: Programming Language :: Python :: 3.10
Classifier: Programming Language :: Python :: 3.11
Classifier: Programming Language :: Python :: 3.12
Classifier: Programming Language :: Python :: 3.13
Classifier: License :: OSI Approved :: MIT License
Classifier: Topic :: Scientific/Engineering :: Artificial Intelligence
Summary: getting structured outputs from LLMs
Keywords: structured outputs,agents,llm
Author: Abhishek Tripathi <abhishek.tripathi456@gmail.com>
Author-email: Abhishek Tripathi <abhishek.tripathi456@gmail.com>
Requires-Python: >=3.8
Project-URL: Homepage, https://github.com/TwistingTwists/json_partial
Project-URL: Source, https://github.com/TwistingTwists/json_partial
